CHANGES
LICENSE
MANIFEST.in
README.md
setup.cfg
setup.py
bin/cred-gen
bin/cred-server
cred/__init__.py
cred/app.py
cred/config.py
cred/database.py
cred/exceptions.py
cred/routes.py
cred/common/__init__.py
cred/common/util.py
cred/models/__init__.py
cred/models/apikey.py
cred/models/client.py
cred/models/event.py
cred/models/subscribe.py
cred/resources/__init__.py
cred/resources/apikeys.py
cred/resources/auth.py
cred/resources/clients.py
cred/resources/clients_events.py
cred/resources/events.py
cred/test/__init__.py
cred/test/test_apikeys.py
cred/test/test_auth.py
cred/test/test_clients.py
cred/test/test_clients_events.py
cred/test/test_events.py
cred/test/util.py
cred_server.egg-info/PKG-INFO
cred_server.egg-info/SOURCES.txt
cred_server.egg-info/dependency_links.txt
cred_server.egg-info/requires.txt
cred_server.egg-info/top_level.txt