Metadata-Version: 1.1
Name: cred-server
Version: 0.2.19
Summary: Connected Reactive Electronic Devices.
Home-page: https://github.com/Tehnix/cred-server
Author: Tehnix
Author-email: ckl@codetalk.io
License: BSD
Download-URL: https://github.com/Tehnix/cred-server/tarball/v0.2.19
Platform: UNKNOWN
Classifier: Development Status :: 1 - Planning
Classifier: Environment :: Console
Classifier: Intended Audience :: Developers
Classifier: Intended Audience :: System Administrators
Classifier: License :: OSI Approved :: BSD License
Classifier: Operating System :: MacOS :: MacOS X
Classifier: Operating System :: POSIX
Classifier: Programming Language :: Python :: 3 :: Only
Classifier: Topic :: Home Automation
